[
  {
    "id": "cs1",
    "question": "도지(Doji) 캔들의 핵심 특징은?",
    "options": [
      "몸통이 매우 길다",
      "시가와 종가가 거의 같다",
      "꼬리가 없다",
      "거래량이 매우 많다"
    ],
    "answer": 1,
    "explanation": "도지는 시가와 종가가 거의 같아 몸통이 매우 작거나 없는 캔들로, 매수세와 매도세의 균형 또는 우유부단을 나타냅니다."
  },
  {
    "id": "cs2",
    "question": "해머(Hammer) 캔들이 강세 반전 신호가 되려면 어디에서 나타나야 하나요?",
    "options": [
      "상승 추세의 고점",
      "하락 추세의 저점",
      "횡보 구간의 중간",
      "어디서든 강세 신호"
    ],
    "answer": 1,
    "explanation": "해머는 하락 추세의 바닥에서 나타날 때 강세 반전 신호입니다. 같은 형태가 상승 추세 고점에서 나타나면 행잉맨(Hanging Man)으로 약세 신호가 됩니다."
  },
  {
    "id": "cs3",
    "question": "강세 장악형(Bullish Engulfing)의 구성은?",
    "options": [
      "큰 양봉 다음에 작은 음봉",
      "작은 음봉 다음에 큰 양봉이 완전히 감싸는 형태",
      "세 개의 연속 양봉",
      "긴 위꼬리를 가진 음봉"
    ],
    "answer": 1,
    "explanation": "강세 장악형은 작은 음봉 뒤에 그 몸통을 완전히 감싸는 큰 양봉이 나타나는 패턴으로, 매수세가 매도세를 압도했음을 보여줍니다."
  },
  {
    "id": "cs4",
    "question": "샛별(Morning Star) 패턴은 몇 개의 캔들로 구성되나요?",
    "options": [
      "1개",
      "2개",
      "3개",
      "4개"
    ],
    "answer": 2,
    "explanation": "샛별은 3개의 캔들로 구성됩니다: 큰 음봉 → 작은 몸통(도지 포함) → 큰 양봉. 하락 추세에서 상승 반전을 시사합니다."
  },
  {
    "id": "cs5",
    "question": "적삼병(Three White Soldiers)의 특징이 아닌 것은?",
    "options": [
      "세 개의 연속 양봉",
      "각 캔들이 이전 캔들보다 높은 곳에서 마감",
      "긴 위꼬리가 있어야 한다",
      "하락 추세 후에 나타나면 반전 신호"
    ],
    "answer": 2,
    "explanation": "적삼병은 세 개의 연속 양봉이 점진적으로 높은 종가를 기록하는 패턴입니다. 긴 위꼬리가 있으면 오히려 신뢰도가 떨어집니다."
  },
  {
    "id": "cs6",
    "question": "캔들 패턴의 신뢰도를 높이는 가장 효과적인 방법은?",
    "options": [
      "더 짧은 시간봉으로 전환하여 확인",
      "거래량, 보조지표와 함께 복합적으로 분석",
      "같은 패턴이 연속으로 나타날 때까지 기다림",
      "패턴의 크기가 클수록 무조건 신뢰"
    ],
    "answer": 1,
    "explanation": "캔들 패턴은 단독으로 사용할 때 오신호가 많습니다. RSI 과매도/과매수, 거래량 급증, 지지/저항선과 같은 다른 요소와 함께 확인하면 신뢰도가 크게 높아집니다."
  },
  {
    "id": "cs7",
    "question": "도지 샛별(Doji Morning Star)이 일반 샛별(Morning Star)보다 더 강력한 반전 신호인 이유는?",
    "options": [
      "캔들 수가 더 많기 때문",
      "가운데 캔들이 도지여서 매수·매도 세력의 완전한 균형을 나타내기 때문",
      "양봉의 몸통이 더 크기 때문",
      "하락 추세가 더 길 때 나타나기 때문"
    ],
    "answer": 1,
    "explanation": "도지 샛별의 중간 캔들은 시가와 종가가 동일한 도지로, 매수·매도 세력이 완전히 균형을 이룬 극도의 불확실성을 의미합니다. 이후 큰 양봉이 나타나면 세력 전환이 더욱 명확하게 확인됩니다."
  },
  {
    "id": "cs8",
    "question": "캔들 패턴에서 '컨텍스트(context)'가 중요한 이유를 가장 잘 설명한 것은?",
    "options": [
      "패턴은 어느 위치에서 나타나든 동일한 의미를 가진다",
      "같은 패턴도 상승 추세, 하락 추세, 지지/저항 여부에 따라 의미가 달라진다",
      "컨텍스트보다 패턴의 크기가 더 중요하다",
      "높은 변동성 구간에서만 패턴이 유효하다"
    ],
    "answer": 1,
    "explanation": "예를 들어 해머는 하락 추세 바닥에서는 강세 반전 신호이지만, 상승 추세 중간에 나타나면 의미가 약합니다. 패턴이 주요 지지선이나 피보나치 수준 근처에서 형성될 때 신뢰도가 높아집니다."
  },
  {
    "id": "cs9",
    "question": "강세 장악형(Bullish Engulfing) 패턴이 실패 신호로 전환되는 경우는?",
    "options": [
      "양봉 다음 날 갭 상승으로 시작할 때",
      "패턴 형성 후 가격이 음봉의 저점 아래로 이탈할 때",
      "거래량이 평균보다 높을 때",
      "RSI가 50 이하일 때"
    ],
    "answer": 1,
    "explanation": "강세 장악형 형성 후 가격이 패턴의 저점(음봉의 저가) 아래로 이탈하면 패턴 실패입니다. 이를 미리 인식하고 손절가를 해당 수준 아래에 설정하는 것이 리스크 관리의 핵심입니다."
  },
  {
    "id": "cs10",
    "question": "저녁별(Evening Star) 패턴에 대한 설명으로 옳은 것은?",
    "options": [
      "하락 추세에서 나타나는 강세 반전 패턴이다",
      "상승 추세에서 나타나며 큰 양봉 → 작은 몸통 → 큰 음봉으로 구성된다",
      "두 개의 캔들로 구성된 반전 패턴이다",
      "샛별(Morning Star)과 동일한 의미를 가진다"
    ],
    "answer": 1,
    "explanation": "저녁별은 샛별의 반대로, 상승 추세 고점에서 나타나는 약세 반전 패턴입니다. 큰 양봉 → 작은 몸통(갭 발생 시 더 강력) → 큰 음봉의 3캔들 구조로 구성됩니다."
  },
  {
    "id": "cs11",
    "question": "캔들의 몸통 비율(Body Ratio)을 계산하는 공식으로 올바른 것은?",
    "options": [
      "(고가 - 저가) / 시가 × 100",
      "|종가 - 시가| / (고가 - 저가) × 100",
      "(종가 - 시가) / 거래량 × 100",
      "(고가 + 저가) / 2 - 시가"
    ],
    "answer": 1,
    "explanation": "몸통 비율은 전체 범위(고가 - 저가) 중 몸통(|종가 - 시가|)이 차지하는 비율입니다. 예를 들어 시가 100, 종가 108, 고가 110, 저가 99이면 몸통 = 8, 전체 범위 = 11, 몸통 비율 ≈ 72.7%입니다. 비율이 높을수록 한쪽 세력이 강하게 지배했음을 나타냅니다."
  },
  {
    "id": "cs12",
    "question": "[계산] 어떤 캔들의 시가 50,000원, 종가 50,200원, 고가 51,000원, 저가 49,500원일 때 위꼬리 길이는?",
    "options": [
      "500원",
      "800원",
      "1,500원",
      "200원"
    ],
    "answer": 1,
    "explanation": "위꼬리 길이 = 고가 - max(시가, 종가) = 51,000 - 50,200 = 800원입니다. 위꼬리는 장중 고점까지 올라갔다가 매도세에 밀려 내려온 구간을 나타냅니다."
  },
  {
    "id": "cs13",
    "question": "[계산] 시가 10,000원, 종가 9,400원, 고가 10,100원, 저가 9,000원인 음봉 캔들의 몸통 비율은?",
    "options": [
      "약 27%",
      "약 54%",
      "약 78%",
      "약 40%"
    ],
    "answer": 1,
    "explanation": "몸통 = |종가 - 시가| = |9,400 - 10,000| = 600원. 전체 범위 = 고가 - 저가 = 10,100 - 9,000 = 1,100원. 몸통 비율 = 600 / 1,100 × 100 ≈ 54.5%입니다. 몸통이 전체 범위의 절반 이상을 차지하므로 매도세가 어느 정도 우위에 있었음을 나타냅니다."
  },
  {
    "id": "cs14",
    "question": "해머(Hammer) 캔들의 유효성 판단 기준으로 가장 일반적으로 사용되는 아래꼬리 조건은?",
    "options": [
      "아래꼬리가 몸통의 1배 이상",
      "아래꼬리가 몸통의 2배 이상",
      "아래꼬리가 몸통의 0.5배 이상",
      "아래꼬리 길이가 100원 이상"
    ],
    "answer": 1,
    "explanation": "일반적으로 해머로 인정받으려면 아래꼬리가 몸통 길이의 최소 2배 이상이어야 합니다. 예를 들어 몸통이 300원이면 아래꼬리는 600원 이상이어야 강한 매수세가 저점을 지지했다는 신호로 해석됩니다."
  },
  {
    "id": "cs15",
    "question": "[계산] 강세 장악형 패턴에서 음봉의 몸통이 시가 5,200원 → 종가 5,000원이고, 뒤이은 양봉이 시가 4,950원 → 종가 5,350원일 때, 이 패턴이 유효한 장악형인가?",
    "options": [
      "아니다 — 양봉의 시가가 음봉 종가보다 낮아 무효이다",
      "그렇다 — 양봉 몸통(400원)이 음봉 몸통(200원)을 완전히 감싼다",
      "아니다 — 양봉 종가가 음봉 시가보다 낮아야 한다",
      "아니다 — 갭 없이 시가가 이어져야 장악형이 성립한다"
    ],
    "answer": 1,
    "explanation": "음봉 몸통: 5,200 → 5,000 (범위: 5,000~5,200, 크기 200원). 양봉 몸통: 4,950 → 5,350 (범위: 4,950~5,350, 크기 400원). 양봉의 시가(4,950)가 음봉 종가(5,000)보다 낮고, 양봉 종가(5,350)가 음봉 시가(5,200)보다 높으므로 음봉 몸통을 완전히 감쌉니다. 유효한 강세 장악형입니다."
  },
  {
    "id": "cs16",
    "question": "[계산] 도지 캔들 판별 기준: 시가 30,000원, 종가 30,150원, 고가 30,800원, 저가 29,500원일 때 몸통 비율은? 일반적으로 몸통 비율이 몇 % 이하이면 도지로 분류하나요?",
    "options": [
      "약 11.5%; 10% 이하",
      "약 11.5%; 20% 이하",
      "약 23%; 10% 이하",
      "약 5%; 5% 이하"
    ],
    "answer": 0,
    "explanation": "몸통 = |종가 - 시가| = |30,150 - 30,000| = 150원. 전체 범위 = 고가 - 저가 = 30,800 - 29,500 = 1,300원. 몸통 비율 = 150 / 1,300 × 100 ≈ 11.5%. 일반적으로 몸통 비율이 전체 범위의 10% 이하일 때 도지로 분류합니다. 이 경우 11.5%로 경계선 근처이며, 분석가에 따라 '도지에 가까운 스피닝 탑'으로 구분하기도 합니다."
  },
  {
    "id": "cs17",
    "question": "[계산] 핀바(Pin Bar) 캔들의 시가 20,000원, 종가 20,300원, 고가 20,400원, 저가 18,500원일 때 아래꼬리 대 몸통 비율은?",
    "options": [
      "약 3배",
      "약 5배",
      "약 7배",
      "약 10배"
    ],
    "answer": 2,
    "explanation": "몸통 = |종가 - 시가| = |20,300 - 20,200| — 실제 계산: 종가 20,300 - 시가 20,000 = 300원. 아래꼬리 = min(시가, 종가) - 저가 = 20,000 - 18,500 = 1,500원. 비율 = 1,500 / 300 = 5배. 아래꼬리가 몸통의 5배로 강한 하단 매수세가 유입됐음을 나타냅니다."
  },
  {
    "id": "cs18",
    "question": "[계산] 샛별(Morning Star) 패턴에서 세 번째 양봉의 '되돌림 비율'을 계산합니다. 첫 번째 음봉: 시가 10,000원 → 종가 8,000원, 세 번째 양봉: 종가 9,200원일 때 첫 번째 음봉 하락폭 대비 되돌림 비율은?",
    "options": [
      "40%",
      "50%",
      "60%",
      "80%"
    ],
    "answer": 2,
    "explanation": "첫 번째 음봉 하락폭 = 10,000 - 8,000 = 2,000원. 세 번째 양봉의 되돌림 = 9,200 - 8,000 = 1,200원. 되돌림 비율 = 1,200 / 2,000 × 100 = 60%. 일반적으로 세 번째 양봉이 첫 번째 음봉 하락폭의 50% 이상을 회복할수록 샛별 패턴의 강도가 높다고 판단합니다."
  }
]
